{
  "app-msg-4-workload-12": {
    "app-msg-4-workload-11": 16
  },
  "app-msg-4-workload-11": {
    "app-msg-4-workload-12": 16
  },
  "app-msg-7-workload-3": {
    "app-msg-7-workload-0": 14
  },
  "app-msg-7-workload-0": {
    "app-msg-7-workload-3": 14,
    "app-msg-7-workload-16": 9,
    "app-msg-7-workload-8": 21,
    "app-msg-7-workload-20": 11
  },
  "app-msg-4-workload-2": {
    "app-msg-4-workload-0": 29
  },
  "app-msg-4-workload-0": {
    "app-msg-4-workload-2": 29,
    "app-msg-4-workload-30": 24
  },
  "app-msg-5-workload-29": {
    "app-msg-5-workload-0": 21
  },
  "app-msg-5-workload-0": {
    "app-msg-5-workload-29": 21,
    "app-msg-5-workload-28": 19,
    "app-msg-5-workload-9": 30,
    "app-msg-5-workload-22": 29,
    "app-msg-5-workload-13": 30,
    "app-msg-5-workload-8": 11,
    "app-msg-5-workload-20": 16,
    "app-msg-5-workload-17": 23,
    "app-msg-5-workload-38": 10,
    "app-msg-5-workload-2": 7
  },
  "app-msg-2-workload-20": {
    "app-msg-2-workload-0": 18
  },
  "app-msg-2-workload-0": {
    "app-msg-2-workload-20": 18,
    "app-msg-2-workload-23": 18,
    "app-msg-2-workload-11": 15
  },
  "app-msg-5-workload-28": {
    "app-msg-5-workload-0": 19
  },
  "app-api-comp-3-workload-17": {
    "app-api-comp-3-workload-16": 26
  },
  "app-api-comp-3-workload-16": {
    "app-api-comp-3-workload-17": 26
  },
  "app-api-comp-9-workload-23": {
    "app-api-comp-9-workload-15": 24
  },
  "app-api-comp-9-workload-15": {
    "app-api-comp-9-workload-23": 24
  },
  "app-msg-5-workload-9": {
    "app-msg-5-workload-0": 30,
    "app-msg-5-workload-10": 20
  },
  "app-msg-2-workload-5": {
    "app-msg-2-workload-6": 8
  },
  "app-msg-2-workload-6": {
    "app-msg-2-workload-5": 8
  },
  "app-api-comp-8-workload-18": {
    "app-api-comp-8-workload-17": 11
  },
  "app-api-comp-8-workload-17": {
    "app-api-comp-8-workload-18": 11
  },
  "app-msg-7-workload-13": {
    "app-msg-7-workload-12": 12
  },
  "app-msg-7-workload-12": {
    "app-msg-7-workload-13": 12
  },
  "app-api-comp-8-workload-16": {
    "app-api-comp-8-workload-15": 29
  },
  "app-api-comp-8-workload-15": {
    "app-api-comp-8-workload-16": 29
  },
  "app-msg-5-workload-12": {
    "app-msg-5-workload-11": 17
  },
  "app-msg-5-workload-11": {
    "app-msg-5-workload-12": 17
  },
  "app-msg-5-workload-27": {
    "app-msg-5-workload-26": 9
  },
  "app-msg-5-workload-26": {
    "app-msg-5-workload-27": 9
  },
  "app-api-comp-9-workload-29": {
    "app-api-comp-9-workload-28": 26
  },
  "app-api-comp-9-workload-28": {
    "app-api-comp-9-workload-29": 26
  },
  "app-msg-1-workload-14": {
    "app-msg-1-workload-0": 17
  },
  "app-msg-1-workload-0": {
    "app-msg-1-workload-14": 17,
    "app-msg-1-workload-20": 25,
    "app-msg-1-workload-5": 9
  },
  "app-api-comp-3-workload-5": {
    "app-api-comp-3-workload-4": 27
  },
  "app-api-comp-3-workload-4": {
    "app-api-comp-3-workload-5": 27,
    "app-api-comp-3-workload-7": 27
  },
  "app-msg-5-workload-22": {
    "app-msg-5-workload-0": 29
  },
  "app-msg-5-workload-13": {
    "app-msg-5-workload-0": 30
  },
  "app-api-comp-6-workload-18": {
    "app-api-comp-6-workload-15": 7
  },
  "app-api-comp-6-workload-15": {
    "app-api-comp-6-workload-18": 7
  },
  "app-msg-11-workload-3": {
    "app-msg-11-workload-2": 25
  },
  "app-msg-11-workload-2": {
    "app-msg-11-workload-3": 25,
    "app-msg-11-workload-0": 30
  },
  "app-api-comp-8-workload-11": {
    "app-api-comp-8-workload-10": 22
  },
  "app-api-comp-8-workload-10": {
    "app-api-comp-8-workload-11": 22,
    "app-api-comp-8-workload-9": 13
  },
  "app-api-comp-9-workload-20": {
    "app-api-comp-9-workload-19": 14
  },
  "app-api-comp-9-workload-19": {
    "app-api-comp-9-workload-20": 14,
    "app-api-comp-9-workload-18": 14
  },
  "app-msg-5-workload-8": {
    "app-msg-5-workload-0": 11
  },
  "app-msg-4-workload-30": {
    "app-msg-4-workload-0": 24
  },
  "app-api-comp-8-workload-12": {
    "app-api-comp-8-workload-13": 25
  },
  "app-api-comp-8-workload-13": {
    "app-api-comp-8-workload-12": 25
  },
  "app-msg-0-workload-18": {
    "app-msg-0-workload-0": 8
  },
  "app-msg-0-workload-0": {
    "app-msg-0-workload-18": 8,
    "app-msg-0-workload-14": 10,
    "app-msg-0-workload-5": 24,
    "app-msg-0-workload-1": 5
  },
  "app-msg-11-workload-5": {
    "app-msg-11-workload-4": 18
  },
  "app-msg-11-workload-4": {
    "app-msg-11-workload-5": 18
  },
  "app-msg-11-workload-6": {
    "app-msg-11-workload-0": 18
  },
  "app-msg-11-workload-0": {
    "app-msg-11-workload-6": 18,
    "app-msg-11-workload-11": 11,
    "app-msg-11-workload-21": 14,
    "app-msg-11-workload-13": 22,
    "app-msg-11-workload-2": 30
  },
  "app-msg-10-workload-11": {
    "app-msg-10-workload-0": 27
  },
  "app-msg-10-workload-0": {
    "app-msg-10-workload-11": 27
  },
  "app-msg-5-workload-10": {
    "app-msg-5-workload-9": 20
  },
  "app-msg-11-workload-11": {
    "app-msg-11-workload-0": 11
  },
  "app-msg-7-workload-16": {
    "app-msg-7-workload-0": 9
  },
  "app-msg-4-workload-9": {
    "app-msg-4-workload-8": 30
  },
  "app-msg-4-workload-8": {
    "app-msg-4-workload-9": 30
  },
  "app-msg-5-workload-15": {
    "app-msg-5-workload-14": 16
  },
  "app-msg-5-workload-14": {
    "app-msg-5-workload-15": 16
  },
  "app-api-comp-9-workload-2": {
    "app-api-comp-9-workload-3": 19
  },
  "app-api-comp-9-workload-3": {
    "app-api-comp-9-workload-2": 19
  },
  "app-msg-5-workload-20": {
    "app-msg-5-workload-0": 16
  },
  "app-msg-5-workload-17": {
    "app-msg-5-workload-0": 23
  },
  "app-msg-7-workload-5": {
    "app-msg-7-workload-6": 11
  },
  "app-msg-7-workload-6": {
    "app-msg-7-workload-5": 11
  },
  "app-msg-7-workload-8": {
    "app-msg-7-workload-0": 21
  },
  "app-msg-2-workload-23": {
    "app-msg-2-workload-0": 18
  },
  "app-msg-2-workload-11": {
    "app-msg-2-workload-0": 15
  },
  "app-msg-11-workload-21": {
    "app-msg-11-workload-0": 14
  },
  "app-msg-2-workload-26": {
    "app-msg-2-workload-27": 8
  },
  "app-msg-2-workload-27": {
    "app-msg-2-workload-26": 8
  },
  "app-api-comp-9-workload-18": {
    "app-api-comp-9-workload-19": 14
  },
  "app-msg-0-workload-3": {
    "app-msg-0-workload-4": 27
  },
  "app-msg-0-workload-4": {
    "app-msg-0-workload-3": 27
  },
  "app-msg-4-workload-27": {
    "app-msg-4-workload-26": 5
  },
  "app-msg-4-workload-26": {
    "app-msg-4-workload-27": 5
  },
  "app-msg-11-workload-13": {
    "app-msg-11-workload-0": 22
  },
  "app-msg-2-workload-19": {
    "app-msg-2-workload-18": 24
  },
  "app-msg-2-workload-18": {
    "app-msg-2-workload-19": 24
  },
  "app-msg-0-workload-14": {
    "app-msg-0-workload-0": 10
  },
  "app-msg-7-workload-9": {
    "app-msg-7-workload-10": 21
  },
  "app-msg-7-workload-10": {
    "app-msg-7-workload-9": 21
  },
  "app-msg-1-workload-20": {
    "app-msg-1-workload-0": 25
  },
  "app-msg-5-workload-38": {
    "app-msg-5-workload-0": 10
  },
  "app-msg-0-workload-20": {
    "app-msg-0-workload-19": 22
  },
  "app-msg-0-workload-19": {
    "app-msg-0-workload-20": 22
  },
  "app-api-comp-8-workload-9": {
    "app-api-comp-8-workload-10": 13
  },
  "app-api-comp-3-workload-7": {
    "app-api-comp-3-workload-4": 27
  },
  "app-msg-0-workload-5": {
    "app-msg-0-workload-0": 24
  },
  "app-msg-5-workload-2": {
    "app-msg-5-workload-0": 7
  },
  "app-msg-0-workload-1": {
    "app-msg-0-workload-0": 5
  },
  "app-msg-7-workload-20": {
    "app-msg-7-workload-0": 11
  },
  "app-msg-1-workload-5": {
    "app-msg-1-workload-0": 9
  },
  "app-msg-5-workload-36": {
    "app-msg-5-workload-37": 19
  },
  "app-msg-5-workload-37": {
    "app-msg-5-workload-36": 19
  }
}